<?xml version="1.0" encoding="utf-8" standalone="yes" ?>
<StringTableList
xmlns:xsi="http://www.w3.org/2001/XMLSchema-instance"
xsi:noNamespaceSchemaLocation="../../../../Game/Data/Schema/Lib/StringTable.xsd">

<!-- GameModeDefText.xml -->
  
  <StringTable>
    <Label>GameMode_Sandbox_Name</Label>
    <String>Sandbox</String>
  </StringTable>

  <StringTable>
    <Label>GameMode_Sandbox_Desc</Label>
    <String>Standard rules apply</String>
  </StringTable>
  
  <StringTable>
    <Label>GameMode_Arena_Name</Label>
    <String>Arena</String>
  </StringTable>

  <StringTable>
    <Label>GameMode_Arena_Desc</Label>
    <String>No AI players and the human players are locked at war.</String>
  </StringTable>
  
  <StringTable>
    <Label>GameMode_Agenda_Name</Label>
    <String>Agenda</String>
  </StringTable>
  
  <StringTable>
    <Label>GameMode_Agenda_Desc</Label>
    <String>An objective is randomly assigned to all human players. The first to complete it wins the game.</String>
  </StringTable>

  <StringTable>
    <Label>GameMode_HiddenAgenda_Name</Label>
    <String>Hidden Agenda</String>
  </StringTable>
  
  <StringTable>
    <Label>GameMode_HiddenAgenda_Desc</Label>
    <String>Randomly assigned an objective that you must meet to win the game. Only you know what your agenda is.</String>
  </StringTable>

  <StringTable>
    <Label>GameMode_Survival_Name</Label>
    <String>Survival</String>
  </StringTable>

  <StringTable>
    <Label>GameMode_Survival_Desc</Label>
    <String>Humans are permanently at war with the AI players and the AI players slowly gain bonuses. The humans will die, the winner is the one who lasts the longest.</String>
  </StringTable>
  
</StringTableList>
