<?xml version="1.0" encoding="utf-8" standalone="yes" ?>
<BattleTacticList
xmlns:xsi="http://www.w3.org/2001/XMLSchema-instance"
xsi:noNamespaceSchemaLocation="../Schema/BattleTacticDefs.xsd">

	<BattleTactic>
		<InternalName>BattleTactic_Balanced</InternalName>
		<DisplayName>BattleTactic_Balanced_Name</DisplayName>
		<Description>BattleTactic_Balanced_Description</Description>
		<Icon>Gfx/Icons/Tactics/Tactics_Balanced.png</Icon>
<!--		<Preclusions>
			<Stat>
				<Option>
					<Name>ScavengersAbility</Name>
				</Option>
			</Stat>
		</Preclusions> -->
	</BattleTactic>

<!--  <BattleTactic>
    <InternalName>BattleTactic_Assault</InternalName>
    <DisplayName>BattleTactic_Assault_Name</DisplayName>
    <Description>BattleTactic_Assault_Description</Description>
    <Icon>Gfx/Icons/Tactics/Tactics_Assault.png</Icon>
    <Triggers>
      <OnEvent>OnBattleSetup</OnEvent>
      <Scope>Local</Scope>
      <Target>
        <TargetType>Faction</TargetType>
      </Target>
      <Lifetime>Battle</Lifetime>
      <Modifier>
        <EffectType>BattleLength</EffectType>
        <Scope>Local</Scope>
        <Target>
          <TargetType>Faction</TargetType>
        </Target>
        <BonusType>Flat</BonusType>
        <Value>0.5</Value>
			</Modifier>
		</Triggers>
		<Triggers>
			<OnEvent>OnBattleSetup</OnEvent>
			<Scope>Local</Scope>
			<Target>
				<TargetType>AllShipsInFleet</TargetType>
			</Target>
			<Lifetime>Battle</Lifetime>
			<Modifier>
				<EffectType>SwarmAbility</EffectType>
				<Scope>Local</Scope>
				<Target>
					<TargetType>Ship</TargetType>
				</Target>
				<BonusType>Flat</BonusType>
				<Value>1</Value>
      </Modifier>
    </Triggers>
    <Triggers>
      <OnEvent>OnBattleSetup</OnEvent>
      <Scope>Local</Scope>
      <Target>
        <TargetType>AllShipsInFleet</TargetType>
      </Target>
      <Lifetime>Battle</Lifetime>
      <Modifier>
        <EffectType>ShieldStrength</EffectType>
        <Scope>Local</Scope>
        <Target>
          <TargetType>Ship</TargetType>
        </Target>
        <BonusType>Multiplier</BonusType>
        <Value>-0.25</Value>
      </Modifier>
      <Modifier>
        <EffectType>ArmorRating</EffectType>
        <Scope>Local</Scope>
        <Target>
          <TargetType>Ship</TargetType>
        </Target>
        <BonusType>Multiplier</BonusType>
        <Value>-0.25</Value>
      </Modifier>
      <Modifier>
        <EffectType>PointDefense</EffectType>
        <Scope>Local</Scope>
        <Target>
          <TargetType>Ship</TargetType>
        </Target>
        <BonusType>Multiplier</BonusType>
        <Value>-0.25</Value>
      </Modifier>
      <Modifier>
        <EffectType>Acceleration</EffectType>
        <Scope>Local</Scope>
        <Target>
          <TargetType>Ship</TargetType>
        </Target>
        <BonusType>Multiplier</BonusType>
        <Value>2.0</Value>
      </Modifier>
      <Modifier>
        <EffectType>TacticalSpeed</EffectType>
        <Scope>Local</Scope>
        <Target>
          <TargetType>Ship</TargetType>
        </Target>
        <BonusType>Multiplier</BonusType>
        <Value>2.0</Value>
      </Modifier>
    </Triggers>
		<Prerequ>
			<Tag>
				<Option>Attacker</Option>
			</Tag>
		</Prerequ>
		<Preclusions>
			<Techs>
				<Option>WarMachine</Option>
			</Techs>
		</Preclusions>
	</BattleTactic>

  <BattleTactic>
    <InternalName>BattleTactic_Skirmish</InternalName>
    <DisplayName>BattleTactic_Skirmish_Name</DisplayName>
    <Description>BattleTactic_Skirmish_Description</Description>
    <Icon>Gfx/Icons/Tactics/Tactics_Balanced.png</Icon>
    <Triggers>
      <OnEvent>OnBattleSetup</OnEvent>
      <Scope>Local</Scope>
      <Target>
        <TargetType>AllShipsInFleet</TargetType>
      </Target>
      <Lifetime>Battle</Lifetime>
      <Modifier>
        <EffectType>EscapeAbility</EffectType>
        <Scope>Local</Scope>
        <Target>
          <TargetType>Ship</TargetType>
        </Target>
        <BonusType>Flat</BonusType>
        <Value>1</Value>
      </Modifier>
      <Modifier>
        <EffectType>EscapeChance</EffectType>
        <Scope>Local</Scope>
        <Target>
          <TargetType>Ship</TargetType>
        </Target>
        <BonusType>Flat</BonusType>
        <Value>1.0</Value>
      </Modifier>
    </Triggers>
    <Prerequ>
      <Tag>
        <Option>Attacker</Option>
      </Tag>
    </Prerequ>
  </BattleTactic>

  <BattleTactic>
    <InternalName>BattleTactic_DefensiveFire</InternalName>
    <DisplayName>BattleTactic_DefensiveFire_Name</DisplayName>
    <Description>BattleTactic_DefensiveFire_Description</Description>
    <Icon>Gfx/Icons/Tactics/Tactics_DefensiveFire.png</Icon>
    <Triggers>
      <OnEvent>OnBattleSetup</OnEvent>
      <Scope>Local</Scope>
      <Target>
        <TargetType>AllShipsInFleet</TargetType>
      </Target>
      <Lifetime>Battle</Lifetime>
      <Modifier>
        <EffectType>ShieldStrength</EffectType>
        <Scope>Local</Scope>
        <Target>
          <TargetType>Ship</TargetType>
        </Target>
        <BonusType>Multiplier</BonusType>
        <Value>0.5</Value>
      </Modifier>
      <Modifier>
        <EffectType>ArmorRating</EffectType>
        <Scope>Local</Scope>
        <Target>
          <TargetType>Ship</TargetType>
        </Target>
        <BonusType>Multiplier</BonusType>
        <Value>0.5</Value>
      </Modifier>
      <Modifier>
        <EffectType>PointDefense</EffectType>
        <Scope>Local</Scope>
        <Target>
          <TargetType>Ship</TargetType>
        </Target>
        <BonusType>Multiplier</BonusType>
        <Value>0.5</Value>
      </Modifier>
      <Modifier>
        <EffectType>BeamAttack</EffectType>
        <Scope>Local</Scope>
        <Target>
          <TargetType>Ship</TargetType>
        </Target>
        <BonusType>Multiplier</BonusType>
        <Value>-0.5</Value>
      </Modifier>
      <Modifier>
        <EffectType>KineticAttack</EffectType>
        <Scope>Local</Scope>
        <Target>
          <TargetType>Ship</TargetType>
        </Target>
        <BonusType>Multiplier</BonusType>
        <Value>-0.5</Value>
      </Modifier>
      <Modifier>
        <EffectType>MissileAttack</EffectType>
        <Scope>Local</Scope>
        <Target>
          <TargetType>Ship</TargetType>
        </Target>
        <BonusType>Multiplier</BonusType>
        <Value>-0.5</Value>
      </Modifier>
    </Triggers>
    <Prerequ>
      <Tag>
        <Option>Defender</Option>
      </Tag>
    </Prerequ>
    <Preclusions>
      <Techs>
        <Option>Fortification</Option>
      </Techs>
    </Preclusions>
  </BattleTactic>

  <BattleTactic>
    <InternalName>BattleTactic_Retreat</InternalName>
    <DisplayName>BattleTactic_Retreat_Name</DisplayName>
    <Description>BattleTactic_Retreat_Description</Description>
    <Icon>Gfx/Icons/Tactics/Tactics_Retreat.png</Icon>
    <Triggers>
      <OnEvent>OnBattleSetup</OnEvent>
      <Scope>Local</Scope>
      <Target>
        <TargetType>Faction</TargetType>
      </Target>
      <Lifetime>Battle</Lifetime>
      <Modifier>
        <EffectType>BattleLength</EffectType>
        <Scope>Local</Scope>
        <Target>
          <TargetType>Faction</TargetType>
        </Target>
        <BonusType>Flat</BonusType>
        <Value>-0.5</Value>
      </Modifier>
    </Triggers>
    <Triggers>
      <OnEvent>OnBattleSetup</OnEvent>
      <Scope>Local</Scope>
      <Target>
        <TargetType>AllShipsInFleet</TargetType>
      </Target>
      <Lifetime>Battle</Lifetime>
      <Modifier>
        <EffectType>WeaponsDisabled</EffectType>
        <Scope>Local</Scope>
        <Target>
          <TargetType>Ship</TargetType>
        </Target>
        <BonusType>Flat</BonusType>
        <Value>1</Value>
      </Modifier>
      <Modifier>
        <EffectType>RetreatAbility</EffectType>
        <Scope>Local</Scope>
        <Target>
          <TargetType>Ship</TargetType>
        </Target>
        <BonusType>Flat</BonusType>
        <Value>1</Value>
      </Modifier>
    </Triggers>
    <Prerequ>
      <Tag>
        <Option>Defender</Option>
      </Tag>
    </Prerequ>
  </BattleTactic>

  <BattleTactic>
    <InternalName>BattleTactic_NoComingBack</InternalName>
    <DisplayName>BattleTactic_NoComingBack_Name</DisplayName>
    <Description>BattleTactic_NoComingBack_Description</Description>
    <Icon>Gfx/Icons/Tactics/Tactics_NoComingBack.png</Icon>
    <Triggers>
      <OnEvent>OnBattleSetup</OnEvent>
      <Scope>Local</Scope>
      <Target>
        <TargetType>AllShipsInFleet</TargetType>
      </Target>
      <Lifetime>Battle</Lifetime>
      <Modifier>
        <EffectType>SuicideAttackAbility</EffectType>
        <Scope>Local</Scope>
        <Target>
          <TargetType>Ship</TargetType>
        </Target>
        <BonusType>Flat</BonusType>
        <Value>1</Value>
      </Modifier>
    </Triggers>
    <Prerequ>
      <RaceTrait>
        <Option>ZealotsAbility</Option>
      </RaceTrait>
    </Prerequ>
  </BattleTactic>

  <BattleTactic>
    <InternalName>BattleTactic_Capture</InternalName>
    <DisplayName>BattleTactic_Capture_Name</DisplayName>
    <Description>BattleTactic_Capture_Description</Description>
    <Icon>Gfx/Icons/Tactics/Tactics_Balanced.png</Icon>
    <Triggers>
      <OnEvent>OnBattleSetup</OnEvent>
      <Scope>Local</Scope>
      <Target>
        <TargetType>Faction</TargetType>
      </Target>
      <Lifetime>Battle</Lifetime>
      <Modifier>
        <EffectType>ScavengersChance</EffectType>
        <Target>
          <TargetType>Faction</TargetType>
        </Target>
        <BonusType>Flat</BonusType>
        <Value>1.0</Value>
      </Modifier>
    </Triggers>
    <Prerequ>
      <Stat>
				<Option>
          <Name>ScavengersAbility</Name>
        </Option>
			</Stat>
    </Prerequ>
  </BattleTactic>

  <BattleTactic>
    <InternalName>BattleTactic_StandFirm</InternalName>
    <DisplayName>BattleTactic_StandFirm_Name</DisplayName>
    <Description>BattleTactic_StandFirm_Description</Description>
    <Icon>Gfx/Icons/Tactics/Tactics_Balanced.png</Icon>
    <Triggers>
      <OnEvent>OnBattleSetup</OnEvent>
      <Scope>Local</Scope>
      <Target>
        <TargetType>AllShipsInFleet</TargetType>
      </Target>
      <Lifetime>Battle</Lifetime>
      <Modifier>
        <EffectType>KineticRange</EffectType>
        <Scope>Local</Scope>
        <Target>
          <TargetType>Ship</TargetType>
        </Target>
        <BonusType>Multiplier</BonusType>
        <Value>0.5</Value>
      </Modifier>
      <Modifier>
        <EffectType>BeamRange</EffectType>
        <Scope>Local</Scope>
        <Target>
          <TargetType>Ship</TargetType>
        </Target>
        <BonusType>Multiplier</BonusType>
        <Value>0.5</Value>
      </Modifier>
      <Modifier>
        <EffectType>MissileRange</EffectType>
        <Scope>Local</Scope>
        <Target>
          <TargetType>Ship</TargetType>
        </Target>
        <BonusType>Multiplier</BonusType>
        <Value>0.5</Value>
      </Modifier>
      <Modifier>
        <EffectType>Acceleration</EffectType>
        <Scope>Local</Scope>
        <Target>
          <TargetType>Ship</TargetType>
        </Target>
        <BonusType>Multiplier</BonusType>
        <Value>-100.0</Value>
      </Modifier>
      <Modifier>
        <EffectType>TacticalSpeed</EffectType>
        <Scope>Local</Scope>
        <Target>
          <TargetType>Ship</TargetType>
        </Target>
        <BonusType>Multiplier</BonusType>
        <Value>-100.0</Value>
      </Modifier>
    </Triggers>
    <Prerequ>
      <Techs>
        <Option>Fortification</Option>
      </Techs>
      <Tag>
        <Option>Defender</Option>
      </Tag>
    </Prerequ>
  </BattleTactic>

  <BattleTactic>
    <InternalName>BattleTactic_Surround</InternalName>
    <DisplayName>BattleTactic_Surround_Name</DisplayName>
    <Description>BattleTactic_Surround_Description</Description>
    <Icon>Gfx/Icons/Tactics/Tactics_Balanced.png</Icon>
    <Triggers>
      <OnEvent>OnBattleSetup</OnEvent>
      <Scope>Local</Scope>
      <Target>
        <TargetType>AllShipsInFleet</TargetType>
      </Target>
      <Lifetime>Battle</Lifetime>
      <Modifier>
        <EffectType>SurroundAbility</EffectType>
        <Scope>Local</Scope>
        <Target>
          <TargetType>Ship</TargetType>
        </Target>
        <BonusType>Flat</BonusType>
        <Value>1</Value>
      </Modifier>
    </Triggers>
		<Triggers>
			<OnEvent>OnBattleSetup</OnEvent>
			<Scope>Local</Scope>
			<Target>
				<TargetType>AllShipsInFleet</TargetType>
			</Target>
			<Lifetime>Battle</Lifetime>
			<Modifier>
				<EffectType>ShieldStrength</EffectType>
				<Scope>Local</Scope>
				<Target>
					<TargetType>Ship</TargetType>
				</Target>
				<BonusType>Multiplier</BonusType>
				<Value>-0.25</Value>
			</Modifier>
			<Modifier>
				<EffectType>ArmorRating</EffectType>
				<Scope>Local</Scope>
				<Target>
					<TargetType>Ship</TargetType>
				</Target>
				<BonusType>Multiplier</BonusType>
				<Value>-0.25</Value>
			</Modifier>
			<Modifier>
				<EffectType>PointDefense</EffectType>
				<Scope>Local</Scope>
				<Target>
					<TargetType>Ship</TargetType>
				</Target>
				<BonusType>Multiplier</BonusType>
				<Value>-0.25</Value>
			</Modifier>
		</Triggers>
		<Prerequ>
			<Techs>
				<Option>WarMachine</Option>
			</Techs>
			<Tag>
				<Option>Attacker</Option>
			</Tag>
		</Prerequ>
		<Preclusions>
			<Tag>
				<Option>FleetOfOne</Option>
			</Tag>
		</Preclusions>
	</BattleTactic> -->

<!--	<BattleTactic>
		<InternalName>BattleTactic_Swarm</InternalName>
		<DisplayName>BattleTactic_Swarm_Name</DisplayName>	
		<Description>BattleTactic_Swarm_Description</Description>
    <Icon>Gfx/Icons/Tactics/Tactics_Balanced.png</Icon>
		<Triggers>
			<OnEvent>OnBattleSetup</OnEvent>
			<Scope>Local</Scope>
			<Target>
				<TargetType>Faction</TargetType>
			</Target>
			<Lifetime>Battle</Lifetime>
			<Modifier>
				<EffectType>BattleLength</EffectType>
				<Scope>Local</Scope>
				<Target>
					<TargetType>Faction</TargetType>
				</Target>
				<BonusType>Flat</BonusType>
				<Value>2.0</Value>
			</Modifier>
		</Triggers>
		<Triggers>
			<OnEvent>OnBattleSetup</OnEvent>
			<Scope>Local</Scope>
			<Target>
				<TargetType>AllShipsInFleet</TargetType>
			</Target>
			<Lifetime>Battle</Lifetime>
			<Modifier>
				<EffectType>SwarmAbility</EffectType>
				<Scope>Local</Scope>
				<Target>
					<TargetType>Ship</TargetType>
				</Target>
				<BonusType>Flat</BonusType>
				<Value>1</Value>
			</Modifier>
		</Triggers>
		<Preclusions>
			<Tag>
				<Option>FleetOfOne</Option>
			</Tag>
		</Preclusions>
	</BattleTactic> -->

</BattleTacticList>
